README.md
pyproject.toml
setup.cfg
setup.py
foam/__init__.py
foam/atmosphere.py
foam/dielectric.py
foam/geomag.py
foam/ionosphere.py
foam/ocean.py
foam/sky.py
foam/solver.py
foam/spacecraft.py
foam/assets/__init__.py
foam/assets/galaxy/__init__.py
foam/assets/magneticfield/__init__.py
foam/assets/ocean/__init__.py
foam/utils/__init__.py
foam/utils/antenna.py
foam/utils/config.py
foam/utils/mk.py
foam/utils/plots.py
foam/utils/reader.py
foam/utils/retrieval_plots.py
foam_rtm.egg-info/PKG-INFO
foam_rtm.egg-info/SOURCES.txt
foam_rtm.egg-info/dependency_links.txt
foam_rtm.egg-info/requires.txt
foam_rtm.egg-info/top_level.txt