Metadata-Version: 2.1
Name: foam-rtm
Version: 0.1.1
Summary: The Forward Ocean/Atmosphere Microwave Radiative Transfer Model
Home-page: UNKNOWN
Author: Alex B. Akins
Author-email: alexander.akins@jpl.nasa.gov
License: Apache
Platform: UNKNOWN
Requires-Python: >=3.8
